qiskit_scheduling_extension/__init__.py
qiskit_scheduling_extension/compact.py
qiskit_scheduling_extension/plugin.py
qiskit_scheduling_extension-0.2.0.dist-info/AUTHORS
qiskit_scheduling_extension-0.2.0.dist-info/LICENSE.txt
qiskit_scheduling_extension-0.2.0.dist-info/METADATA
qiskit_scheduling_extension-0.2.0.dist-info/WHEEL
qiskit_scheduling_extension-0.2.0.dist-info/entry_points.txt
qiskit_scheduling_extension-0.2.0.dist-info/pbr.json
qiskit_scheduling_extension-0.2.0.dist-info/top_level.txt
qiskit_scheduling_extension-0.2.0.dist-info/RECORD
