Metadata-Version: 2.1
Name: qiskit-scheduling-extension
Version: 0.2.0
Summary: Qiskit transpiler plugins for advanced scheduling
Home-page: https://github.com/qiskit-community/qiskit-scheduling-extension
Author: Toshinari Itoko
Author-email: itoko@jp.ibm.com
License: Apache-2
Project-URL: Bug Tracker, https://github.com/qiskit-community/qiskit-scheduling-extension/issues
Classifier: Intended Audience :: Information Technology
Classifier: Intended Audience :: System Administrators
Classifier: Intended Audience :: Developers
Classifier: License :: OSI Approved :: Apache Software License
Classifier: Operating System :: POSIX :: Linux
Classifier: Programming Language :: Python
Classifier: Programming Language :: Python :: 3
Classifier: Programming Language :: Python :: 3.8
Classifier: Programming Language :: Python :: 3.9
Classifier: Programming Language :: Python :: 3.10
Requires-Python: >=3.8
License-File: LICENSE.txt
License-File: AUTHORS
Requires-Dist: pbr >=5.7.0
Requires-Dist: qiskit >=0.44
